smart_decorator/__init__.py
smart_decorator/_decorator_factory.py
smart_decorator/_types.py
smart_decorator/method_decorator.py
smart_decorator/method_decorator.pyi
smart_decorator/simple_decorator.py
smart_decorator/simple_decorator.pyi
smart_decorator/smart_decorator.py
smart_decorator/smart_decorator.pyi
smart_decorator/types.py
smart_decorator/utils.py
smart_decorator-0.1.0.dist-info/LICENSE
smart_decorator-0.1.0.dist-info/METADATA
smart_decorator-0.1.0.dist-info/WHEEL
smart_decorator-0.1.0.dist-info/RECORD
