Metadata-Version: 2.3
Name: smart-decorator
Version: 0.1.0
Summary: A modern library for creating decorators. Static-typed.
Author: Marckie Zeender
Author-email: mkzeender@gmail.com
Requires-Python: >=3.9
Classifier: Programming Language :: Python :: 3
Classifier: Programming Language :: Python :: 3.9
Classifier: Programming Language :: Python :: 3.10
Classifier: Programming Language :: Python :: 3.11
Classifier: Programming Language :: Python :: 3.12
Classifier: Programming Language :: Python :: 3.13
